mitosis/__init__.py
mitosis/__main__.py
mitosis/_db.py
mitosis/_disk.py
mitosis/_strings.py
mitosis/_typing.py
mitosis/_version.py
mitosis/py.typed
mitosis/tests/__init__.py
mitosis/tests/bad_return_experiment.py
mitosis/tests/mock_legacy.py
mitosis/tests/mock_paper.py
mitosis/tests/mock_part1.py
mitosis/tests/mock_part2.py
mitosis/tests/pyproject_malformed.toml
mitosis/tests/pyproject_missing.toml
mitosis/tests/test_all.py
mitosis/tests/test_cli.py
mitosis/tests/test_pyproject.toml
mitosis-0.6.1.dist-info/licenses/LICENSE
mitosis-0.6.1.dist-info/METADATA
mitosis-0.6.1.dist-info/WHEEL
mitosis-0.6.1.dist-info/entry_points.txt
mitosis-0.6.1.dist-info/top_level.txt
mitosis-0.6.1.dist-info/RECORD
