Metadata-Version: 2.4
Name: mitosis
Version: 0.6.1
Summary: Reproduce Machine Learning experiments easily
Author-email: Jake Stevens-Haas <jacob.stevens.haas@gmail.com>
License: MIT
Project-URL: homepage, https://github.com/Jacob-Stevens-Haas/mitosis
Keywords: Machine Learning,Science,Mathematics,Experiments
Classifier: Development Status :: 4 - Beta
Classifier: Programming Language :: Python
Classifier: Framework :: Jupyter
Classifier: Intended Audience :: Developers
Classifier: Intended Audience :: Science/Research
Classifier: License :: OSI Approved :: MIT License
Classifier: Natural Language :: English
Classifier: Operating System :: POSIX :: Linux
Classifier: Operating System :: MacOS
Classifier: Operating System :: Microsoft :: Windows
Classifier: Programming Language :: SQL
Classifier: Topic :: Documentation
Classifier: Topic :: Scientific/Engineering
Classifier: Topic :: Scientific/Engineering :: Artificial Intelligence
Classifier: Topic :: Software Development :: Libraries :: Python Modules
Classifier: Topic :: Software Development :: Testing
Classifier: Topic :: Software Development :: Version Control :: Git
Classifier: Topic :: Text Processing :: Markup
Requires-Python: >=3.10
License-File: LICENSE
Requires-Dist: dill
Requires-Dist: GitPython
Requires-Dist: importlib_metadata
Requires-Dist: ipykernel
Requires-Dist: matplotlib
Requires-Dist: nbconvert
Requires-Dist: nbclient
Requires-Dist: nbformat
Requires-Dist: sqlalchemy>=2.0
Requires-Dist: toml
Requires-Dist: types-toml
Provides-Extra: dev
Requires-Dist: pytest<8.0.0,>=6.0.0; extra == "dev"
Requires-Dist: pytest-cov; extra == "dev"
Requires-Dist: flake8; extra == "dev"
Requires-Dist: flake8-comprehensions>=3.1.0; extra == "dev"
Requires-Dist: black; extra == "dev"
Requires-Dist: coverage; extra == "dev"
Requires-Dist: mypy; extra == "dev"
Requires-Dist: pre-commit; extra == "dev"
Requires-Dist: pytest-lazy-fixture; extra == "dev"
Requires-Dist: sphinx; extra == "dev"
Requires-Dist: codecov; extra == "dev"
Requires-Dist: myst-parser; extra == "dev"
Dynamic: license-file
